example_pkg/__init__.py
sportpursuit/__init__.py
sportpursuit/sportpursuit.py
tests/__init__.py
tests/sportpursuit_test.py
sportpursuit-0.0.5.dist-info/LICENSE
sportpursuit-0.0.5.dist-info/METADATA
sportpursuit-0.0.5.dist-info/WHEEL
sportpursuit-0.0.5.dist-info/top_level.txt
sportpursuit-0.0.5.dist-info/RECORD
