Metadata-Version: 2.1
Name: sportpursuit
Version: 0.0.5
Summary: A package containing key sp functions
Home-page: https://github.com/georgebiggs/sp_py_pkg
Author: georgebiggs
Author-email: george.biggs@sportpursuit.com
License: UNKNOWN
Platform: UNKNOWN
Classifier: Programming Language :: Python :: 3
Classifier: License :: OSI Approved :: MIT License
Classifier: Operating System :: OS Independent
Requires-Python: >=3.6
Requires-Dist: pandas
Requires-Dist: psycopg2
